wgrd_cons_parsers/__init__.py
wgrd_cons_parsers/baf.py
wgrd_cons_parsers/boobs.py
wgrd_cons_parsers/common.py
wgrd_cons_parsers/compress_ndfbin.py
wgrd_cons_parsers/cons_utils.py
wgrd_cons_parsers/decompress_ndfbin.py
wgrd_cons_parsers/dic.py
wgrd_cons_parsers/dictionary.py
wgrd_cons_parsers/edat.py
wgrd_cons_parsers/ess.py
wgrd_cons_parsers/mesh.py
wgrd_cons_parsers/ppk.py
wgrd_cons_parsers/scenario.py
wgrd_cons_parsers/sformat.py
wgrd_cons_parsers/skeleton.py
wgrd_cons_parsers/spk.py
wgrd_cons_parsers/tgv.py
wgrd_cons_parsers/tms.py
wgrd_cons_parsers/utils.py
wgrd_cons_parsers/version.py
wgrd_cons_parsers/wargameprofile.py
wgrd_cons_parsers/win.py
wgrd_cons_parsers/xyz.py
wgrd_cons_parsers-0.3.1.dist-info/licenses/LICENSE
wgrd_cons_parsers-0.3.1.dist-info/METADATA
wgrd_cons_parsers-0.3.1.dist-info/WHEEL
wgrd_cons_parsers-0.3.1.dist-info/top_level.txt
wgrd_cons_parsers-0.3.1.dist-info/RECORD
