Metadata-Version: 2.4
Name: wgrd_cons_parsers
Version: 0.3.1
Summary: Tools for working with the game files of the game Wargame: Red Dragon
Author-email: End <wgrd@3nd.io>
Requires-Python: >=3.10
License-File: LICENSE
Requires-Dist: conshex
Requires-Dist: pytest
Dynamic: license-file
